{
  "$schema": "../node_modules/@tauri-apps/cli/config.schema.json",
  "productName": "Stash",
  "version": "0.1.1",
  "identifier": "com.asyncat.stash",
  "build": {
    "frontendDist": "../dist",
    "devUrl": "http://localhost:5173",
    "beforeDevCommand": "npm run dev",
    "beforeBuildCommand": "npm run build"
  },
  "app": {
    "windows": [
      {
        "title": "Stash",
        "width": 1024,
        "height": 768,
        "minWidth": 800,
        "minHeight": 600,
        "resizable": true,
        "fullscreen": false,
        "decorations": true,
        "shadow": true
      }
    ],
    "security": {
      "csp": "default-src 'self'; img-src 'self' https: http: data:; style-src 'self' 'unsafe-inline'; script-src 'self'; connect-src ipc: http://ipc.localhost"
    }
  },
  "plugins": {
    "updater": {
      "pubkey": "dW50cnVzdGVkIGNvbW1lbnQ6IG1pbmlzaWduIHB1YmxpYyBrZXk6IDg3Q0JGQUE1MkMyMDE4QUMKUldTc0dDQXNwZnJMaDl6cUM4R0RNcmlRVEVtNmNQcEZPSE12Mkk4WDd0dG1pcmFEMXdSTTd1YSsK",
      "endpoints": [
        "https://github.com/nicosql/Stash/releases/latest/download/latest.json"
      ]
    }
  },
  "bundle": {
    "active": true,
    "targets": "all",
    "icon": [
      "icons/32x32.png",
      "icons/128x128.png",
      "icons/128x128@2x.png",
      "icons/icon.icns",
      "icons/icon.ico"
    ]
  }
}
